<annotation>
	<folder>Train</folder>
	<filename>train (296).jpg</filename>
	<path>D:\Projects\receipt_detection\receipt_data\Jsons\Images\Train\train (296).jpg</path>
	<source>
		<database>Unknown</database>
	</source>
	<size>
		<width>800</width>
		<height>600</height>
		<depth>3</depth>
	</size>
	<segmented>0</segmented>
	<object>
		<name>doc</name>
		<pose>Unspecified</pose>
		<truncated>0</truncated>
		<difficult>0</difficult>
		<bndbox>
			<xmin>261</xmin>
			<ymin>35</ymin>
			<xmax>565</xmax>
			<ymax>528</ymax>
		</bndbox>
	</object>
</annotation>
